esensorlib/README.md
esensorlib/__init__.py
esensorlib/accl_fn.py
esensorlib/imu_fn.py
esensorlib/reg_interface.py
esensorlib/sensor_device.py
esensorlib/spi_port.py
esensorlib/uart_port.py
esensorlib/vib_fn.py
esensorlib/example/__init__.py
esensorlib/example/accl_logger.py
esensorlib/example/helper.py
esensorlib/example/imu_logger.py
esensorlib/example/vibe_logger.py
esensorlib/model/__init__.py
esensorlib/model/ma342vd10.py
esensorlib/model/ma352ad10.py
esensorlib/model/ma370ad10.py
esensorlib/model/mcore.py
esensorlib/model/mg320.py
esensorlib/model/mg354.py
esensorlib/model/mg355qdg0.py
esensorlib/model/mg364pdc0.py
esensorlib/model/mg364pdca.py
esensorlib/model/mg365pdc1.py
esensorlib/model/mg365pdf1.py
esensorlib/model/mg366pdg0.py
esensorlib/model/mg370pdf1.py
esensorlib/model/mg370pdg0.py
esensorlib/model/mg370pds0.py
esensorlib/model/mg370pdt0.py
esensorlib/model/mg570pr20.py
esensorlib-2.1.0.dist-info/METADATA
esensorlib-2.1.0.dist-info/WHEEL
esensorlib-2.1.0.dist-info/licenses/LICENSE
esensorlib-2.1.0.dist-info/RECORD
