Metadata-Version: 2.4
Name: esensorlib
Version: 2.1.0
Summary: Python driver package for Epson Sensing System devices
Author-email: Raymond Chow <raymond.chow@ea.epson.com>
License: MIT License
License-File: LICENSE
Keywords: accelerometer,gyroscope,imu,inertial,navigation,sensor
Classifier: License :: OSI Approved :: MIT License
Classifier: Operating System :: OS Independent
Classifier: Programming Language :: Python :: 3
Classifier: Topic :: Scientific/Engineering
Classifier: Topic :: Software Development :: Embedded Systems
Classifier: Topic :: Software Development :: Libraries :: Python Modules
Classifier: Topic :: Software Development :: Localization
Classifier: Topic :: System :: Hardware :: Hardware Drivers
Requires-Python: >=3.8
Requires-Dist: loguru>=0.7.3
Requires-Dist: pyserial>=3.5
Requires-Dist: tabulate>=0.9.0
Requires-Dist: tqdm>=4.62.3
